{
  "packageName": "Hubitat OpenHASP",
  "author": "NichUK",
  "version": "0.3.1",
  "minimumHEVersion": "2.3.0",
  "dateReleased": "2026-06-21",
  "licenseFile": "https://raw.githubusercontent.com/NichUK/Hubitat-OpenHASP/main/LICENSE",
  "documentationLink": "https://github.com/NichUK/Hubitat-OpenHASP/blob/main/README.md",
  "communityLink": "",
  "releaseNotes": "Prevents managed-control echoes from being reprocessed as commands and stops panel-originated light changes from writing back to the same OpenHASP switch or slider when Hubitat confirms the state.",
  "apps": [
    {
      "id": "c407c68a-1ce9-4bf6-94b1-2710505bbd30",
      "name": "OpenHASP Manager",
      "namespace": "nichuk",
      "location": "https://raw.githubusercontent.com/NichUK/Hubitat-OpenHASP/main/apps/openhasp-manager.groovy",
      "required": true,
      "oauth": false,
      "primary": true
    },
    {
      "id": "2f5586b9-b2aa-4d16-9ff5-c47cfdf6aee9",
      "name": "OpenHASP Panel",
      "namespace": "nichuk",
      "location": "https://raw.githubusercontent.com/NichUK/Hubitat-OpenHASP/main/apps/openhasp-panel.groovy",
      "required": true,
      "oauth": false,
      "primary": false
    }
  ],
  "drivers": [
    {
      "id": "f8aa89cd-c1cf-4974-adf6-7e6fce44d7e4",
      "name": "OpenHASP Text Label",
      "namespace": "nichuk",
      "location": "https://raw.githubusercontent.com/NichUK/Hubitat-OpenHASP/main/drivers/openhasp-text-label.groovy",
      "required": true
    }
  ]
}
